yunorm/__init__.py
yunorm/db/__init__.py
yunorm/db/error.py
yunorm/db/field.py
yunorm/db/handler.py
yunorm/db/handler_new.py
yunorm/db/models.py
yunorm/db/sql.py
yunorm/utils/__init__.py
yunorm/utils/tools.py
yunorm-0.4.3.dist-info/DESCRIPTION.rst
yunorm-0.4.3.dist-info/METADATA
yunorm-0.4.3.dist-info/RECORD
yunorm-0.4.3.dist-info/WHEEL
yunorm-0.4.3.dist-info/metadata.json
yunorm-0.4.3.dist-info/top_level.txt
