Metadata-Version: 2.0
Name: yunorm
Version: 0.4.3
Summary: A small ORM but It's very practical
Home-page: https://github.com/yunsonbai/yunorm
Author: yunsonbai
Author-email: 1572120849@qq.com
License: Apache
Platform: UNKNOWN
Classifier: Programming Language :: Python :: 3.5
Classifier: Programming Language :: Python :: 3.6
Classifier: License :: OSI Approved :: Apache Software License
Classifier: Operating System :: OS Independent
Requires-Dist: mysqlclient (==1.3.14)
Requires-Dist: mysql-connector-python (==8.0.15)
